twitter_to_sqlite/__init__.py
twitter_to_sqlite/archive.py
twitter_to_sqlite/cli.py
twitter_to_sqlite/migrations.py
twitter_to_sqlite/utils.py
twitter_to_sqlite-0.22.dist-info/LICENSE
twitter_to_sqlite-0.22.dist-info/METADATA
twitter_to_sqlite-0.22.dist-info/WHEEL
twitter_to_sqlite-0.22.dist-info/entry_points.txt
twitter_to_sqlite-0.22.dist-info/top_level.txt
twitter_to_sqlite-0.22.dist-info/RECORD
