Metadata-Version: 2.1
Name: twitter-to-sqlite
Version: 0.22
Summary: Save data from Twitter to a SQLite database
Home-page: https://datasette.io/tools/twitter-to-sqlite
Author: Simon Willison
License: Apache License, Version 2.0
Project-URL: Issues, https://github.com/dogsheep/twitter-to-sqlite/issues
Project-URL: CI, https://github.com/dogsheep/twitter-to-sqlite/actions
Project-URL: Changelog, https://github.com/dogsheep/twitter-to-sqlite/releases
Platform: UNKNOWN
License-File: LICENSE
Requires-Dist: sqlite-utils (>=2.4.2)
Requires-Dist: requests-oauthlib (~=1.2.0)
Requires-Dist: python-dateutil
Provides-Extra: test
Requires-Dist: pytest ; extra == 'test'
